mdsync/__init__.py
mdsync/cli.py
mdsync/constants.py
mdsync/converter.py
mdsync/discovery.py
mdsync/platforms/__init__.py
mdsync/platforms/base.py
mdsync/platforms/notion.py
mdsync-0.1.2.dist-info/licenses/LICENSE
tests/test_constants.py
tests/test_converter.py
tests/test_discovery.py
mdsync-0.1.2.dist-info/METADATA
mdsync-0.1.2.dist-info/WHEEL
mdsync-0.1.2.dist-info/entry_points.txt
mdsync-0.1.2.dist-info/top_level.txt
mdsync-0.1.2.dist-info/RECORD
